setup.py
googlecalendarsync/__init__.py
googlecalendarsync/dao.py
googlecalendarsync/googlecalendarsync.py
googlecalendarsync/googlecalendartest.py
googlecalendarsync/googleeventdao.py
googlecalendarsync/request_token.py
googlecalendarsync.egg-info/PKG-INFO
googlecalendarsync.egg-info/SOURCES.txt
googlecalendarsync.egg-info/dependency_links.txt
googlecalendarsync.egg-info/not-zip-safe
googlecalendarsync.egg-info/requires.txt
googlecalendarsync.egg-info/top_level.txt