Metadata-Version: 1.0
Name: googlecalendarsync
Version: 0.1
Summary: Module to sync events from your Google calendar
Home-page: https://bitbucket.org/diamino/googlecalendarsync
Author: Diamino
Author-email: code@diamino.nl
License: MIT
Platform: UNKNOWN
